nimbloon/__init__.py
nimbloon/raccoon.py
nimbloon/trees.py
nimbloon/utils.py
nimbloon/static/header.txt
nimble_raccoon-0.1.1.dist-info/LICENSE
nimble_raccoon-0.1.1.dist-info/METADATA
nimble_raccoon-0.1.1.dist-info/WHEEL
nimble_raccoon-0.1.1.dist-info/top_level.txt
nimble_raccoon-0.1.1.dist-info/RECORD
