Metadata-Version: 2.1
Name: nimble-raccoon
Version: 0.1.1
Summary: A slim and fast implementation of the RACCOON clustering library.
Author-email: Federico Comitani <federico.comitani@gmail.com>
License: GPL-3.0
Project-URL: repository, https://github.com/fcomitani/nimble-raccoon
Keywords: clustering,dimensionality-reduction,iterative,hierarchical-clustering,multi-scale,scale-adaptive,snn,louvain
Classifier: Development Status :: 3 - Alpha
Classifier: Programming Language :: Python :: 3
Requires-Python: >=3.10
License-File: LICENSE
Requires-Dist: pyarrow >=14.0.1
Requires-Dist: numpy >=1.26.2
Requires-Dist: pandas >=2.1.3
Requires-Dist: scikit-learn >=1.3.2
Requires-Dist: scikit-network >=0.31.0
Requires-Dist: umap-learn >=0.5.4
Requires-Dist: anytree >=2.12.0
Requires-Dist: tqdm >=4.66.1
Requires-Dist: pynndescent >=0.5.10
Requires-Dist: matplotlib >=3.8.1
Requires-Dist: loguru >=0.7.2
Requires-Dist: faiss-cpu >=1.7.4
Requires-Dist: toml >=0.10.2
Requires-Dist: pytest >=7.4.3
Provides-Extra: gpu
Requires-Dist: faiss-gpu ; extra == 'gpu'
